README
setup.py
sonyp_rs232c/SonyHWXXES.py
sonyp_rs232c/__init__.py
sonyp_rs232c.egg-info/PKG-INFO
sonyp_rs232c.egg-info/SOURCES.txt
sonyp_rs232c.egg-info/dependency_links.txt
sonyp_rs232c.egg-info/top_level.txt