Metadata-Version: 1.1
Name: sonyp-rs232c
Version: 0.1
Summary: A Python3 class used for controlling a Sony VPL-HWXXES projector via serial connection.
Home-page: https://github.com/R3MRUM/sonyp_rs232c
Author: R3MRUM
Author-email: robpantazopoulos@gmail.com
License: GPLv3+
Keywords: sony projector VPL-HW35ES VPL-HW40ES VPL-HW50ES VPL-HW55ES VPL-HW58ES HW35ES HW40ES HW50ES HW55ES HW58ES
Platform: UNKNOWN
Classifier: Development Status :: 4 - Beta
Classifier: Topic :: Home Automation
Classifier: License :: OSI Approved :: GNU General Public License v3 or later (GPLv3+)
